easyunfold/__init__.py
easyunfold/cli.py
easyunfold/effective_mass.py
easyunfold/plotting.py
easyunfold/procar.py
easyunfold/unfold.py
easyunfold/utils.py
easyunfold/vasp_constant.py
easyunfold/wavecar.py
easyunfold/wavefun.py
easyunfold-0.4.0.dist-info/entry_points.txt
easyunfold-0.4.0.dist-info/licenses/LICENSE
easyunfold-0.4.0.dist-info/WHEEL
easyunfold-0.4.0.dist-info/METADATA
easyunfold-0.4.0.dist-info/RECORD
