Metadata-Version: 2.4
Name: easyunfold
Version: 0.4.0
Summary: Collection of code for band unfolding
Author-email: Bonan Zhu <zhubonan@outlook.com>, Seán Kavanagh <sk2045@cam.ac.uk>
Requires-Python: >=3.7
Classifier: License :: OSI Approved :: MIT License
Classifier: Programming Language :: Python :: 3
License-File: LICENSE
Requires-Dist: scipy>=1.0
Requires-Dist: numpy>=1.0
Requires-Dist: matplotlib>=3.0
Requires-Dist: ase>=3.14
Requires-Dist: spglib>=2.0
Requires-Dist: click
Requires-Dist: monty
Requires-Dist: tqdm>=4.0
Requires-Dist: tabulate>=0.8
Requires-Dist: colormath>=3.0
Requires-Dist: castepxbin>=0.3.0
Requires-Dist: castepinput>=0.1
Requires-Dist: sphinx-click>=4,<5 ; extra == "doc"
Requires-Dist: sphinx-autodoc2>=0.4,<0.5 ; extra == "doc"
Requires-Dist: sphinx-book-theme>=1,<2 ; extra == "doc"
Requires-Dist: sphinx-copybutton>=0.3,<0.4 ; extra == "doc"
Requires-Dist: myst-parser[linkify] ; extra == "doc"
Requires-Dist: sphinx>=6,<7 ; extra == "doc"
Requires-Dist: astroid<3 ; extra == "doc"
Requires-Dist: sumo ; extra == "dos"
Requires-Dist: pre-commit ; extra == "pre-commit"
Requires-Dist: pylint~=2.11 ; extra == "pre-commit"
Requires-Dist: sumo ; extra == "pre-commit"
Requires-Dist: pytest ; extra == "test"
Requires-Dist: pytest-cov ; extra == "test"
Requires-Dist: coverage ; extra == "test"
Requires-Dist: sumo ; extra == "test"
Project-URL: Documentation, https://smtg-Bham.github.io/easyunfold/
Project-URL: Homepage, https://github.com/SMTG-Bham/easyunfold
Provides-Extra: doc
Provides-Extra: dos
Provides-Extra: pre-commit
Provides-Extra: test
